{
    "nome": "DIRETRIZES FAPES PARA HORIZON EUROPE 2021-2027 (1ª ALTERAÇÃO)",
    "descrição": "Edital de fomento FAPES: DIRETRIZES FAPES PARA HORIZON EUROPE 2021-2027 (1ª ALTERAÇÃO)",
    "orgão_fomento": "FAPES",
    "categoria": "chamadas",
    "status": "aberto",
    "data_abertura": "2026-01-01",
    "data_encerramento": "",
    "link": "https://fapes.es.gov.br/Media/fapes/Editais/Diretrizes_Fapes_Horizon_Europe_2021-2027-DITEC_-_16-09-25.pdf",
    "cronograma": [],
    "tags": [
        "fapes",
        "edital"
    ]
}